pdbuild/__init__.py
pdbuild/commandline/__init__.py
pdbuild/commandline/tool.py
pdbuild/core/__init__.py
pdbuild/utiil/__init__.py
pdbuild-0.0.0.dist-info/LICENSE
pdbuild-0.0.0.dist-info/METADATA
pdbuild-0.0.0.dist-info/WHEEL
pdbuild-0.0.0.dist-info/entry_points.txt
pdbuild-0.0.0.dist-info/top_level.txt
pdbuild-0.0.0.dist-info/RECORD
