Metadata-Version: 2.1
Name: pdbuild
Version: 0.0.0
Summary: Cross platform extensable build system
Home-page: https://gitlab.com/pdbuild/pdbuild
Author: Julian Dessecker
License: UNKNOWN
Platform: UNKNOWN
Classifier: Programming Language :: Python :: 3
Classifier: License :: OSI Approved :: MIT License
Classifier: Operating System :: OS Independent
Requires-Python: >=3.8
License-File: LICENSE
Requires-Dist: pdcommandline (==0.1.1)
